piprm/__init__.py
piprm/cmd/__init__.py
piprm/cmd/main.py
piprm/exceptions.py
piprm/http_tools.py
piprm/manager/__init__.py
piprm/manager/factory.py
piprm/manager/pdm.py
piprm/manager/pip.py
piprm/pip_tools.py
piprm/registry.py
piprm-0.3.0.dist-info/LICENSE
piprm-0.3.0.dist-info/METADATA
piprm-0.3.0.dist-info/WHEEL
piprm-0.3.0.dist-info/entry_points.txt
piprm-0.3.0.dist-info/RECORD
