Metadata-Version: 2.1
Name: piprm
Version: 0.3.0
Summary: pip registry manager
License: MIT
Author: wxnacy
Author-email: wxnacy@gmail.com
Requires-Python: >=3.8,<4.0
Classifier: License :: OSI Approved :: MIT License
Classifier: Programming Language :: Python :: 3
Classifier: Programming Language :: Python :: 3.8
Classifier: Programming Language :: Python :: 3.9
Classifier: Programming Language :: Python :: 3.10
Classifier: Programming Language :: Python :: 3.11
Classifier: Programming Language :: Python :: 3.12
Requires-Dist: requests (>=2.32.3,<3.0.0)
Requires-Dist: typer (>=0.12.5,<0.13.0)
